sphinx_compas2_theme/__init__.py
sphinx_compas2_theme/__main__.py
sphinx_compas2_theme/linkcode.py
sphinx_compas2_theme/multisection/theme.conf
sphinx_compas2_theme/shared/static/compas.ico
sphinx_compas2_theme/shared/static/compas_icon.png
sphinx_compas2_theme/shared/static/compas_icon_white.png
sphinx_compas2_theme/shared/static/compas_icon_white_48.png
sphinx_compas2_theme/shared/static/compas_icon_white_96.png
sphinx_compas2_theme/shared/static/compas_white.ico
sphinx_compas2_theme/shared/static/css/_color.scss
sphinx_compas2_theme/shared/static/css/compas.css
sphinx_compas2_theme/sidebaronly/theme.conf
sphinx_compas2_theme/templates/layout.html
sphinx_compas2_theme/templates/multisection-sidebar-nav.html
sphinx_compas2_theme/templates/sidebaronly-navbar-nav.html
sphinx_compas2_theme/templates/sidebaronly-sidebar-footer.html
sphinx_compas2_theme/templates/sidebaronly-sidebar-nav.html
sphinx_compas2_theme/templates/autosummary/attribute.rst
sphinx_compas2_theme/templates/autosummary/base.rst
sphinx_compas2_theme/templates/autosummary/class.rst
sphinx_compas2_theme/templates/autosummary/method.rst
sphinx_compas2_theme-0.1.10.dist-info/AUTHORS.md
sphinx_compas2_theme-0.1.10.dist-info/LICENSE
sphinx_compas2_theme-0.1.10.dist-info/METADATA
sphinx_compas2_theme-0.1.10.dist-info/WHEEL
sphinx_compas2_theme-0.1.10.dist-info/entry_points.txt
sphinx_compas2_theme-0.1.10.dist-info/top_level.txt
sphinx_compas2_theme-0.1.10.dist-info/RECORD
