Metadata-Version: 2.1
Name: sphinx-compas2-theme
Version: 0.1.10
Summary: COMPAS 2 Theme for Sphinx
Home-page: https://github.com/compas-dev/sphinx_compas2_theme
Author: tom van mele
Author-email: tom.v.mele@gmail.com
License: MIT license
Classifier: Development Status :: 4 - Beta
Classifier: Intended Audience :: Developers
Classifier: Topic :: Scientific/Engineering
Classifier: License :: OSI Approved :: MIT License
Classifier: Operating System :: Unix
Classifier: Operating System :: POSIX
Classifier: Operating System :: Microsoft :: Windows
Classifier: Programming Language :: Python
Classifier: Programming Language :: Python :: 3
Classifier: Programming Language :: Python :: 3.8
Classifier: Programming Language :: Python :: 3.9
Classifier: Programming Language :: Python :: 3.10
Classifier: Programming Language :: Python :: Implementation :: CPython
Requires-Python: >=3.8
License-File: LICENSE
License-File: AUTHORS.md
Requires-Dist: compas
Requires-Dist: jinja2 >=3.0
Requires-Dist: numpydoc
Requires-Dist: pydata-sphinx-theme <0.14,>=0.13
Requires-Dist: pydocstyle
Requires-Dist: pytest
Requires-Dist: pytest-mock
Requires-Dist: sphinx
Requires-Dist: sphinx-book-theme
Requires-Dist: sphinx-copybutton
Requires-Dist: sphinx-design
Requires-Dist: sphinx-favicon
Requires-Dist: sphinx-inline-tabs
Requires-Dist: sphinx-remove-toctrees
Requires-Dist: sphinx-togglebutton
Requires-Dist: sphinxcontrib-bibtex
Requires-Dist: sphinxcontrib-youtube
